japronto_jinja2/__init__.py
japronto_jinja2-0.0.1.dist-info/DESCRIPTION.rst
japronto_jinja2-0.0.1.dist-info/METADATA
japronto_jinja2-0.0.1.dist-info/RECORD
japronto_jinja2-0.0.1.dist-info/WHEEL
japronto_jinja2-0.0.1.dist-info/metadata.json
japronto_jinja2-0.0.1.dist-info/top_level.txt
