Metadata-Version: 2.0
Name: japronto-jinja2
Version: 0.0.1
Summary: jinja2 async template renderer for japronto web server
Home-page: UNKNOWN
Author: Misha Behersky
Author-email: bmwant@gmail.com
License: Apache 2
Platform: UNKNOWN
Classifier: License :: OSI Approved :: Apache Software License
Classifier: Intended Audience :: Developers
Classifier: Programming Language :: Python
Classifier: Programming Language :: Python :: 3
Classifier: Programming Language :: Python :: 3.4
Classifier: Programming Language :: Python :: 3.5
Classifier: Topic :: Internet :: WWW/HTTP
Requires-Dist: japronto (<0.2,>=0.1.1)
Requires-Dist: jinja2 (>=2.7)
Provides-Extra: dev
Requires-Dist: alabaster (>=0.6.2); extra == 'dev'
Requires-Dist: coverage (==4.3.4); extra == 'dev'
Requires-Dist: flake8 (==3.3.0); extra == 'dev'
Requires-Dist: japronto (<0.2,>=0.1.1); extra == 'dev'
Requires-Dist: jinja2 (>=2.7); extra == 'dev'
Requires-Dist: pytest (>=3.0.7); extra == 'dev'
Requires-Dist: pytest-cov (==2.4.0); extra == 'dev'
Requires-Dist: sphinx (==1.5.5); extra == 'dev'
Requires-Dist: twine (==1.8.1); extra == 'dev'
